thothctl/__init__.py
thothctl/autocomplete.py
thothctl/cli.py
thothctl/version.py
thothctl/wellcome_banner.py
thothctl/application/__init__.py
thothctl/commands/__init__.py
thothctl/commands/check/__init__.py
thothctl/commands/check/cli.py
thothctl/commands/check/commands/__init__.py
thothctl/commands/check/commands/environment.py
thothctl/commands/check/commands/iac.py
thothctl/commands/check/commands/project.py
thothctl/commands/check/commands/project/__init__.py
thothctl/commands/check/commands/project/iac.py
thothctl/commands/dashboard/__init__.py
thothctl/commands/dashboard/cli.py
thothctl/commands/dashboard/commands/__init__.py
thothctl/commands/dashboard/commands/launch.py
thothctl/commands/document/__init__.py
thothctl/commands/document/cli.py
thothctl/commands/document/commands/__init__.py
thothctl/commands/document/commands/iac.py
thothctl/commands/generate/__init__.py
thothctl/commands/generate/cli.py
thothctl/commands/generate/commands/__init__.py
thothctl/commands/generate/commands/component.py
thothctl/commands/generate/commands/stacks.py
thothctl/commands/init/__init__.py
thothctl/commands/init/cli.py
thothctl/commands/init/commands/__init__.py
thothctl/commands/init/commands/env.py
thothctl/commands/init/commands/project.py
thothctl/commands/init/commands/space.py
thothctl/commands/inventory/__init__.py
thothctl/commands/inventory/cli.py
thothctl/commands/inventory/commands/__init__.py
thothctl/commands/inventory/commands/check.py
thothctl/commands/inventory/commands/iac.py
thothctl/commands/list/__init__.py
thothctl/commands/list/cli.py
thothctl/commands/list/commands/__init__.py
thothctl/commands/list/commands/projects.py
thothctl/commands/list/commands/spaces.py
thothctl/commands/mcp/__init__.py
thothctl/commands/mcp/cli.py
thothctl/commands/mcp/commands/__init__.py
thothctl/commands/mcp/commands/register.py
thothctl/commands/mcp/commands/server.py
thothctl/commands/mcp/commands/status.py
thothctl/commands/mcp/commands/stop.py
thothctl-0.10.7.dist-info/METADATA
thothctl-0.10.7.dist-info/WHEEL
thothctl-0.10.7.dist-info/entry_points.txt
thothctl-0.10.7.dist-info/licenses/LICENSE
thothctl-0.10.7.dist-info/RECORD
