Metadata-Version: 2.1
Name: thothctl
Version: 0.10.7
Summary: A CLI for Developer Control Plane. Accelerate your cloud IaC deployments.
Project-URL: Homepage, https://github.com/thothforge/thothctl
Author-email: Alejandro Velez <velez94@pm.me>
License: Apache-2.0
Requires-Python: >=3.8
Requires-Dist: argcomplete>=3.4.0
Requires-Dist: argparse>=1.4.0
Requires-Dist: azure-devops==7.1.0b4
Requires-Dist: bc-python-hcl2>=0.4.2
Requires-Dist: boto3>=1.34.0
Requires-Dist: checkov==3.2.451
Requires-Dist: click>=8.0.0
Requires-Dist: colorama>=0.4.6
Requires-Dist: cryptography>=41.0.0
Requires-Dist: fastapi>=0.104.0
Requires-Dist: gitdb>=4.0.11
Requires-Dist: gitpython>=3.1.0
Requires-Dist: inquirer>=3.3.0
Requires-Dist: json2html>=1.3.0
Requires-Dist: junit2html>=30.1.3
Requires-Dist: junitparser>=2.0.0
Requires-Dist: mcp>=1.9.4
Requires-Dist: pre-commit>=3.7.1
Requires-Dist: psutil
Requires-Dist: pyfiglet>=1.0.2
Requires-Dist: pymsteams>=0.2.2
Requires-Dist: pytest-cov>=5.0.0
Requires-Dist: pytest>=8.2.2
Requires-Dist: pywin32>=306; sys_platform == 'win32'
Requires-Dist: pyyaml<7.0.0,>=6.0.0
Requires-Dist: requests
Requires-Dist: rich>=13.7.1
Requires-Dist: terraform-compliance>=1.3.48
Requires-Dist: toml>=0.10.2
Requires-Dist: uvicorn>=0.24.0
Requires-Dist: xmltodict>=0.13.0
Requires-Dist: zipp>=3.19.2
Provides-Extra: telemetry
Requires-Dist: opentelemetry-api>=1.20.0; extra == 'telemetry'
Requires-Dist: opentelemetry-exporter-otlp-proto-grpc>=1.20.0; extra == 'telemetry'
Requires-Dist: opentelemetry-instrumentation-logging>=0.41b0; extra == 'telemetry'
Requires-Dist: opentelemetry-sdk>=1.20.0; extra == 'telemetry'
